puush/__init__.py
puush/puush.py
puush.py-1.1.0.dist-info/DESCRIPTION.rst
puush.py-1.1.0.dist-info/METADATA
puush.py-1.1.0.dist-info/RECORD
puush.py-1.1.0.dist-info/WHEEL
puush.py-1.1.0.dist-info/metadata.json
puush.py-1.1.0.dist-info/top_level.txt
