Metadata-Version: 2.0
Name: puush.py
Version: 1.1.0
Summary: A Python module for the Puush (http://puush.me/) API.
Home-page: https://github.com/obskyr/puush.py
Author: Samuel Messner
Author-email: powpowd@gmail.com
License: MIT
Download-URL: https://github.com/obskyr/puush.py/tarball/v1.1.0
Keywords: puush upload filehost rest
Platform: UNKNOWN
Classifier: Development Status :: 5 - Production/Stable
Classifier: Intended Audience :: Developers
Classifier: Programming Language :: Python
Classifier: Natural Language :: English
Classifier: License :: OSI Approved :: MIT License
Classifier: Programming Language :: Python :: 2.7
Classifier: Programming Language :: Python :: 3
Classifier: Programming Language :: Python :: 3.2
Classifier: Programming Language :: Python :: 3.3
Classifier: Programming Language :: Python :: 3.4
Classifier: Programming Language :: Python :: 3.5
Classifier: Topic :: Software Development :: Libraries :: Python Modules
Classifier: Topic :: Utilities
Requires-Dist: requests (>=1.0.0)
